dropbox_langchain/__init__.py
dropbox_langchain/dropbox_files.py
dropbox_langchain-0.11.0.dist-info/LICENSE.txt
dropbox_langchain-0.11.0.dist-info/METADATA
dropbox_langchain-0.11.0.dist-info/WHEEL
dropbox_langchain-0.11.0.dist-info/top_level.txt
dropbox_langchain-0.11.0.dist-info/RECORD
