Metadata-Version: 2.1
Name: dropbox_langchain
Version: 0.11.0
Summary: A Dropbox langchain integration
Home-page: https://github.com/umich-its-ai/langchain-doc-dropbox
Author: University of Michigan
Author-email: noreply@umich.edu
Classifier: Development Status :: 3 - Alpha
Classifier: License :: OSI Approved :: GNU General Public License (GPL)
Requires-Python: >=3.8.1
License-File: LICENSE.txt
Requires-Dist: langchain
Requires-Dist: langchain-community
Requires-Dist: unstructured
Requires-Dist: dropbox
Requires-Dist: beautifulsoup4
Requires-Dist: lxml
Requires-Dist: PyPDF2[crypto]
Requires-Dist: pydantic
Requires-Dist: docx2txt
Requires-Dist: striprtf
